{
	"info": {
		"_postman_id": "cf4bef23-d23b-409f-acfc-7bc70f1f1360",
		"name": "Tradexa",
		"schema": "https://schema.getpostman.com/json/collection/v2.1.0/collection.json",
		"_exporter_id": "32614538"
	},
	"item": [
		{
			"name": "Users",
			"request": {
				"method": "POST",
				"header": [],
				"body": {
					"mode": "raw",
					"raw": "{\n    \"id\": 11,\n    \"name\": \"Kunal\",\n    \"email\": \"kunal@example.com\"\n}\n",
					"options": {
						"raw": {
							"language": "json"
						}
					}
				},
				"url": {
					"raw": "http://127.0.0.1:8000/api/users/",
					"protocol": "http",
					"host": [
						"127",
						"0",
						"0",
						"1"
					],
					"port": "8000",
					"path": [
						"api",
						"users",
						""
					]
				}
			},
			"response": []
		},
		{
			"name": "Products",
			"request": {
				"method": "POST",
				"header": [],
				"body": {
					"mode": "raw",
					"raw": "{\n    \"id\": 11,\n    \"name\": \"Tshirt\",\n    \"price\": 1000.00\n}",
					"options": {
						"raw": {
							"language": "json"
						}
					}
				},
				"url": {
					"raw": "http://127.0.0.1:8000/api/products/",
					"protocol": "http",
					"host": [
						"127",
						"0",
						"0",
						"1"
					],
					"port": "8000",
					"path": [
						"api",
						"products",
						""
					]
				}
			},
			"response": []
		},
		{
			"name": "Orders",
			"request": {
				"method": "POST",
				"header": [],
				"body": {
					"mode": "raw",
					"raw": "{\n    \"id\": 11,\n    \"user_id\": 11,\n    \"product_id\": 11,\n    \"quantity\": 4\n}\n",
					"options": {
						"raw": {
							"language": "json"
						}
					}
				},
				"url": {
					"raw": "http://127.0.0.1:8000/api/orders/",
					"protocol": "http",
					"host": [
						"127",
						"0",
						"0",
						"1"
					],
					"port": "8000",
					"path": [
						"api",
						"orders",
						""
					]
				}
			},
			"response": []
		}
	]
}